{
    "events": [
        {
            "id": "EVT-MSG-ENT-A",
            "companyId": "ENT-A",
            "employeeId": null,
            "contractId": "CTR-ENT-A-HEALTH",
            "date": "2026-03-08",
            "eventType": "messagerie",
            "status": "information",
            "severity": "low",
            "title": "Message du gestionnaire",
            "description": "Demande de verification d une piece justificative."
        },
        {
            "id": "EVT-DSN-ENT-A",
            "companyId": "ENT-A",
            "employeeId": null,
            "contractId": null,
            "date": "2026-03-11",
            "eventType": "erreur_dsn",
            "status": "pending",
            "severity": "high",
            "title": "Erreur DSN bloquante",
            "description": "Controle DSN a corriger avant le prochain envoi."
        },
        {
            "id": "EVT-AR-005",
            "companyId": "ENT-A",
            "employeeId": "SAL-008",
            "contractId": "CTR-ENT-A-DISABILITY",
            "date": "2025-02-03",
            "eventType": "nouvel_at",
            "status": "pending",
            "severity": "high",
            "title": "Ouverture dossier accident travail",
            "description": "Henri Guillot - 7 jours, IJ estimees 563.84 EUR"
        },
        {
            "id": "EVT-AR-001",
            "companyId": "ENT-A",
            "employeeId": "SAL-005",
            "contractId": "CTR-ENT-A-DISABILITY",
            "date": "2025-01-15",
            "eventType": "arret_maladie",
            "status": "pending",
            "severity": "medium",
            "title": "Ouverture dossier maladie",
            "description": "Chloe Berger - 18 jours, IJ estimees 1530.89 EUR"
        },
        {
            "id": "EVT-AR-002",
            "companyId": "ENT-A",
            "employeeId": "SAL-010",
            "contractId": "CTR-ENT-A-DISABILITY",
            "date": "2025-01-20",
            "eventType": "arret_maladie",
            "status": "pending",
            "severity": "medium",
            "title": "Ouverture dossier maladie",
            "description": "Beatrice Moulin - 12 jours, IJ estimees 984.66 EUR"
        },
        {
            "id": "EVT-AR-H01",
            "companyId": "ENT-A",
            "employeeId": "SAL-022",
            "contractId": "CTR-ENT-A-DISABILITY",
            "date": "2024-09-25",
            "eventType": "cloture_dossier",
            "status": "closed",
            "severity": "low",
            "title": "Cloture d un dossier prevoyance",
            "description": "Anna Leroy - dossier cloture apres 15 jours"
        }
    ]
}